Metadata-Version: 2.1
Name: gauext
Version: 0.2.2
Summary: Generic Gaussian External Interface
Home-page: https://github.com/mfsjmenger/gauext
Author: Maximilian F.S.J. Menger
Author-email: m.f.s.j.menger@rug.nl
License: Apache License v2.0
Keywords: Gaussian,Chemistry
Platform: UNKNOWN
Classifier: Development Status :: 2 - Pre-Alpha
Classifier: Intended Audience :: Developers
Classifier: License :: OSI Approved :: Apache Software License
Classifier: Natural Language :: English
Classifier: Programming Language :: Python :: 3.5
Classifier: Programming Language :: Python :: 3.6
Classifier: Programming Language :: Python :: 3.7
Requires-Python: >=3.6
License-File: LICENSE
